SNMatrix/__init__.py
SNMatrix-0.1.dist-info/LICENCE.txt
SNMatrix-0.1.dist-info/METADATA
SNMatrix-0.1.dist-info/WHEEL
SNMatrix-0.1.dist-info/top_level.txt
SNMatrix-0.1.dist-info/RECORD
