Metadata-Version: 2.1
Name: SNMatrix
Version: 0.1
Summary: Basic Matrix Operations For Square Matrices
Author: SHANMUGA NATHAN V
Author-email: Shanmu2224@gmail.com
Classifier: Programming Language :: Python :: 3
Classifier: License :: OSI Approved :: MIT License
Classifier: Operating System :: OS Independent
License-File: LICENCE.txt
